meugooglesheets/__init__.py
meugooglesheets/meugooglesheets.py
meugooglesheets-0.1.6.dist-info/METADATA
meugooglesheets-0.1.6.dist-info/WHEEL
meugooglesheets-0.1.6.dist-info/RECORD
