Metadata-Version: 2.1
Name: meugooglesheets
Version: 0.1.6
Summary: 
Author: leomoraesguitar
Author-email: 123950901+leomoraesguitar@users.noreply.github.com
Requires-Python: >=3.12,<4.0
Classifier: Programming Language :: Python :: 3
Classifier: Programming Language :: Python :: 3.12
Requires-Dist: gspread (==6.1.4)
Requires-Dist: oauth2client (==4.1.3)
